objectfactory/__init__.py
objectfactory/base.py
objectfactory/factory.py
objectfactory/field.py
objectfactory/nested.py
objectfactory/serializable.py
test/__init__.py
test/test_boolean.py
test/test_custom_schema.py
test/test_datetime.py
test/test_enum.py
test/test_factory.py
test/test_fields.py
test/test_float.py
test/test_integer.py
test/test_list.py
test/test_nested.py
test/test_serializable.py
test/test_string.py
test/testmodule/__init__.py
test/testmodule/testclasses.py
objectfactory-0.2.0.dist-info/LICENSE
objectfactory-0.2.0.dist-info/METADATA
objectfactory-0.2.0.dist-info/WHEEL
objectfactory-0.2.0.dist-info/top_level.txt
objectfactory-0.2.0.dist-info/RECORD
