Metadata-Version: 2.2
Name: objectfactory
Version: 0.2.0
Summary: objectfactory is a python package to easily implement the factory design pattern for object creation, serialization, and polymorphism
Home-page: https://github.com/devinaconley/py-object-factory
Author: Devin A. Conley
Author-email: devinaconley@gmail.com
Classifier: Programming Language :: Python :: 3
Classifier: License :: OSI Approved :: MIT License
Classifier: Operating System :: OS Independent
License-File: LICENSE
Requires-Dist: marshmallow<4,>=3
Dynamic: author
Dynamic: author-email
Dynamic: classifier
Dynamic: description
Dynamic: description-content-type
Dynamic: home-page
Dynamic: requires-dist
Dynamic: summary
